datafoundry/__init__.py
datafoundry/_core/__init__.py
datafoundry/_core/api_client.py
datafoundry/_core/postgres_core.py
datafoundry/_core/spark_core.py
datafoundry/_core/version_core.py
datafoundry/_core/dataset/__init__.py
datafoundry/_core/dataset/dataset_core.py
datafoundry/_core/dataset/table_core.py
datafoundry/_dynamic/__init__.py
datafoundry/_dynamic/dataset/InfrastructureDb_67cdcc9916e2eaa728b1882d.py
datafoundry/_dynamic/dataset/IrdDbV2_67ce627463c7f6c1881cb7b8.py
datafoundry/_dynamic/dataset/Mktvng2024_67cddc49c02ec2e05423809d.py
datafoundry/_dynamic/dataset/__init__.py
datafoundry/_dynamic/source/__init__.py
datafoundry/_dynamic/source/mysql/__init__.py
datafoundry/_dynamic/source/postgresql/GreenNodeSource.py
datafoundry/_dynamic/source/postgresql/GreenSourceV2.py
datafoundry/_dynamic/source/postgresql/GreennodeSourceV1.py
datafoundry/_dynamic/source/postgresql/VngMarketing2024.py
datafoundry/_dynamic/source/postgresql/VngMarketingSourceV2.py
datafoundry/_dynamic/source/postgresql/VngMarketingSourceV3.py
datafoundry/_dynamic/source/postgresql/__init__.py
datafoundry/ontology/__init__.py
datafoundry/ontology/datasource/__init__.py
datafoundry/ontology/datasource/postgresql.py
datafoundry-1.0.125.dist-info/METADATA
datafoundry-1.0.125.dist-info/WHEEL
datafoundry-1.0.125.dist-info/top_level.txt
datafoundry-1.0.125.dist-info/RECORD
