Metadata-Version: 2.1
Name: datafoundry
Version: 1.0.125
Summary: A small example package
Home-page: https://github.com/pypa/sampleproject
Author: gada121982
Author-email: gada121982@gmail.com
License: UNKNOWN
Platform: UNKNOWN
Classifier: Programming Language :: Python :: 3
Classifier: License :: OSI Approved :: MIT License
Classifier: Operating System :: OS Independent
Requires-Dist: pandas (>=2.2.3)
Requires-Dist: psycopg2-binary (>=2.9.10)
Requires-Dist: pyspark (>=3.5.1)
Requires-Dist: sqlalchemy (>=2.0.38)
Requires-Dist: trino (>=0.333.0)
